bottle_session.py
bottle_session-1.0.dist-info/LICENSE.txt
bottle_session-1.0.dist-info/METADATA
bottle_session-1.0.dist-info/WHEEL
bottle_session-1.0.dist-info/top_level.txt
bottle_session-1.0.dist-info/RECORD
