Metadata-Version: 1.1
Name: bottle-session
Version: 1.0
Summary: Redis based sessions for bottle.
Home-page: https://bitbucket.org/devries/bottle-session
Author: Christopher De Vries
Author-email: devries@idolstarastronomer.com
License: Artistic
Platform: UNKNOWN
Classifier: Development Status :: 5 - Production/Stable
Classifier: Framework :: Bottle
Classifier: Intended Audience :: Developers
Classifier: License :: OSI Approved :: Artistic License
Classifier: Operating System :: OS Independent
Classifier: Programming Language :: Python
Classifier: Topic :: Internet :: WWW/HTTP :: WSGI :: Application
